genepy/cell_line_mapping-master/python/cell_line_mapper/__init__.py
genepy/cell_line_mapping-master/python/cell_line_mapper/test_mapper.py
genepy/epigenetics/CREME.py
genepy/epigenetics/__init__.py
genepy/epigenetics/chipseq.py
genepy/epigenetics/plot.py
genepy/google/__init__.py
genepy/google/gcp.py
genepy/google/google_sheet.py
genepy/google/gsheet_upload.py
genepy/mutations/__init__.py
genepy/rna/__init__.py
genepy/rna/pyDESeq2.py
genepy/sequencing/__init__.py
genepy/terra/__init__.py
genepy/terra/map_terra_workflow.py
genepy/utils/Datanalytics.py
genepy/utils/__init__.py
genepy/utils/helper.py
genepy/utils/plot.py
Broad_genepy-1.2.6.dist-info/LICENSE
Broad_genepy-1.2.6.dist-info/METADATA
Broad_genepy-1.2.6.dist-info/WHEEL
Broad_genepy-1.2.6.dist-info/top_level.txt
Broad_genepy-1.2.6.dist-info/RECORD
