Metadata-Version: 2.1
Name: Broad-genepy
Version: 1.2.6
Summary: A useful module for any CompBio
Home-page: https://github.com/BroadInstitute/genepy
Author: Jeremie Kalfon
Author-email: jkobject@gmail.com
Classifier: Programming Language :: Python :: 3
Classifier: Intended Audience :: Science/Research
Classifier: Topic :: Scientific/Engineering :: Bio-Informatics
Requires-Python: >=3.5
License-File: LICENSE
Requires-Dist: bokeh (>=2.2)
Requires-Dist: colorcet
Requires-Dist: firecloud-dalmatian (>=0.0.17)
Requires-Dist: gseapy (==0.9.18)
Requires-Dist: gsheets (==0.4.1)
Requires-Dist: gspread (==3.6.0)
Requires-Dist: matplotlib
Requires-Dist: oauth2client (>=4.1.3)
Requires-Dist: pandas
Requires-Dist: pybedtools
Requires-Dist: pyBigWig
Requires-Dist: pysam
Requires-Dist: pytest
Requires-Dist: requests (>=2.24.0)
Requires-Dist: scikit-learn
Requires-Dist: scipy (>=1.0.0)
Requires-Dist: seaborn
Requires-Dist: statsmodels
Requires-Dist: taigapy (>=2.12)
Requires-Dist: venn
Requires-Dist: biomart
